deploy.py
requirement.py
scripts.py
utils.py
deploy_django-0.0.11.dist-info/LICENSE.TXT
deploy_django-0.0.11.dist-info/METADATA
deploy_django-0.0.11.dist-info/WHEEL
deploy_django-0.0.11.dist-info/top_level.txt
deploy_django-0.0.11.dist-info/RECORD
